tunnelgraf/__init__.py
tunnelgraf/config.py
tunnelgraf/constants.py
tunnelgraf/hosts_manager.py
tunnelgraf/interactive_session.py
tunnelgraf/lastpass_secrets.py
tunnelgraf/logger.py
tunnelgraf/nslookup.py
tunnelgraf/run_remote.py
tunnelgraf/transfer.py
tunnelgraf/tunnel_builder.py
tunnelgraf/tunnel_count.py
tunnelgraf/tunnel_definition.py
tunnelgraf/tunnels.py
tunnelgraf-1.2.0.dist-info/METADATA
tunnelgraf-1.2.0.dist-info/WHEEL
tunnelgraf-1.2.0.dist-info/entry_points.txt
tunnelgraf-1.2.0.dist-info/licenses/LICENSE
tunnelgraf-1.2.0.dist-info/RECORD
