Metadata-Version: 2.4
Name: tunnelgraf
Version: 1.2.0
Summary: Hierarchical SSH tunnel management made easy. Securely define and share multihop connection profiles that expose a graph of remote endpoints as localhost.
Project-URL: Homepage, https://github.com/denniswalker/tunnelgraf
Project-URL: Documentation, https://github.com/denniswalker/tunnelgraf/blob/main/README.md
Project-URL: Repository, https://github.com/denniswalker/tunnelgraf
Project-URL: Issues, https://github.com/denniswalker/tunnelgraf/issues
Author-email: Dennis Walker <denniswalker@me.com>
Maintainer-email: Dennis Walker <denniswalker@me.com>
License: MIT License
License-File: LICENSE
Keywords: connectivity,dns,hosts,remote,secrets,ssh,tunnel
Classifier: Development Status :: 3 - Alpha
Classifier: Intended Audience :: System Administrators
Classifier: License :: OSI Approved :: MIT License
Classifier: Programming Language :: Python :: 3
Classifier: Programming Language :: Python :: 3.8
Classifier: Programming Language :: Python :: 3.9
Classifier: Programming Language :: Python :: 3.10
Classifier: Programming Language :: Python :: 3.11
Classifier: Programming Language :: Python :: 3.12
Classifier: Topic :: System :: Networking
Requires-Dist: click>=8.0.6
Requires-Dist: deepmerge~=1.0
Requires-Dist: paramiko~=3.4.0
Requires-Dist: psutil~=6.0.0
Requires-Dist: pydantic~=2.10.0
Requires-Dist: python-hosts~=1.0.5
Requires-Dist: pyyaml~=6.0.0
Requires-Dist: sftpretty~=1.1.6
Requires-Dist: sshtunnel~=0.4.0
Requires-Dist: wcwidth~=0.2.13
Provides-Extra: test
Requires-Dist: pytest-cov>=4.0.0; extra == 'test'
Requires-Dist: pytest>=7.0.0; extra == 'test'
